{
  "date_analyzed": "2025-03-21T23:02:14.308991",
  "ai_related_postings": [
    {
      "date": "previous_month",
      "count": 412
    },
    {
      "date": "current_month",
      "count": 115
    }
  ],
  "growth_rate": -72.0873786407767,
  "top_job_titles": [],
  "top_growing_titles": [
    {
      "title": "Prompt Engineer",
      "count": 0,
      "growth_rate": 96
    },
    {
      "title": "AI Engineer",
      "count": 0,
      "growth_rate": 68
    },
    {
      "title": "Machine Learning Engineer",
      "count": 0,
      "growth_rate": 54
    },
    {
      "title": "NLP Specialist",
      "count": 0,
      "growth_rate": 48
    },
    {
      "title": "Data Scientist",
      "count": 0,
      "growth_rate": 32
    },
    {
      "title": "Data Engineer",
      "count": 0,
      "growth_rate": 26
    }
  ]
}